MANIFEST.in
README.rst
setup.py
docs/CONTRIBUTORS.rst
docs/HISTORY.rst
docs/LICENSE.txt
src/plone/__init__.py
src/plone.jsonapi.core.egg-info/PKG-INFO
src/plone.jsonapi.core.egg-info/SOURCES.txt
src/plone.jsonapi.core.egg-info/dependency_links.txt
src/plone.jsonapi.core.egg-info/entry_points.txt
src/plone.jsonapi.core.egg-info/namespace_packages.txt
src/plone.jsonapi.core.egg-info/not-zip-safe
src/plone.jsonapi.core.egg-info/requires.txt
src/plone.jsonapi.core.egg-info/top_level.txt
src/plone/jsonapi/__init__.py
src/plone/jsonapi/core/.DS_Store
src/plone/jsonapi/core/__init__.py
src/plone/jsonapi/core/configure.zcml
src/plone/jsonapi/core/interfaces.py
src/plone/jsonapi/core/version.py
src/plone/jsonapi/core/browser/__init__.py
src/plone/jsonapi/core/browser/api.py
src/plone/jsonapi/core/browser/configure.zcml
src/plone/jsonapi/core/browser/decorators.py
src/plone/jsonapi/core/browser/helpers.py
src/plone/jsonapi/core/browser/interfaces.py
src/plone/jsonapi/core/browser/router.py
src/plone/jsonapi/core/docs/Readme.txt
src/plone/jsonapi/core/tests/__init__.py
src/plone/jsonapi/core/tests/base.py
src/plone/jsonapi/core/tests/plone.pdf
src/plone/jsonapi/core/tests/test_doctests.py
src/plone/jsonapi/core/tests/test_setup.py