Metadata-Version: 1.1
Name: plone.jsonapi.core
Version: 0.6
Summary: Plone JSON API
Home-page: https://github.com/collective/plone.jsonapi.core
Author: Ramon Bartl
Author-email: rb@ridingbytes.com
License: MIT
Platform: UNKNOWN
Classifier: Programming Language :: Python
Classifier: Framework :: Plone
Classifier: Framework :: Zope2
